[{"token":"foreign","contribution":0.21091769635677338},{"token":"policy","contribution":0.017491936683654785},{"token":"monetary","contribution":0.0042375121265649796},{"token":"minister","contribution":0.0024158686865121126},{"token":"ministry","contribution":0.0023759761825203896},{"token":"affairs","contribution":0.0020384236704558134},{"token":"relations","contribution":0.0005601738230325282},{"token":"adviser","contribution":0.00031698052771389484},{"token":"domestic","contribution":0.00030203332426026464},{"token":"makers","contribution":0.00029101051040925086},{"token":"public","contribution":0.00020370182755868882},{"token":"ashton","contribution":0.00019103329395875335},{"token":"governments","contribution":0.0001889348350232467},{"token":"committee","contribution":0.00018720707157626748},{"token":"economic","contribution":0.0001700419234111905},{"token":"analyst","contribution":0.00016608956502750516},{"token":"government","contribution":0.0001632938365219161},{"token":"fiscal","contribution":0.000160724637680687},{"token":"institute","contribution":0.00015975881251506507},{"token":"immigration","contribution":0.00015050487127155066}]