[{"token":"de","contribution":0.9999499320983887},{"token":"la","contribution":0.00004924261520500295},{"token":"en","contribution":7.317973427234392e-7},{"token":"se","contribution":6.219439541155225e-8},{"token":"à","contribution":1.7379361949565464e-8},{"token":"para","contribution":8.46627745687556e-9},{"token":"por","contribution":5.171602257547647e-9},{"token":"el","contribution":4.693101463004723e-9},{"token":"una","contribution":3.0268305639680193e-9},{"token":"qui","contribution":2.0081767360125014e-9},{"token":"les","contribution":1.326541765322986e-9},{"token":"je","contribution":6.987850853512612e-10},{"token":"como","contribution":6.709974798013718e-10},{"token":"su","contribution":3.63591018404108e-10},{"token":"da","contribution":2.4520238617320445e-10},{"token":"des","contribution":1.8981359539704812e-10},{"token":"le","contribution":1.6641710232079276e-10},{"token":"dans","contribution":1.6063031460511468e-10},{"token":"une","contribution":1.2437587071367773e-10},{"token":"del","contribution":1.0756979335058148e-10}]